igen/__init__.py
igen/__main__.py
igen/api_cmd.py
igen/bind_cmd.py
igen/command.py
igen/config_cmd.py
igen/constants.py
igen/encoder.py
igen/file_header_cmd.py
igen/file_helpers.py
igen/init_cmd.py
igen/json_cmd.py
igen/mock_cmd.py
igen/model.py
igen/pb.py
igen/str_helpers.py
igen/template.py
igen/template_cmd.py
igen/test_cmd.py
igen/vm.py
igen/xcode_cmd.py
igen_templates/__init__.py
igen_templates/base/Assembler.swift
igen_templates/base/FileHeader.swift
igen_templates/base/Navigator.swift
igen_templates/base/NavigatorMock.swift
igen_templates/base/UseCase.swift
igen_templates/base/UseCaseMock.swift
igen_templates/base/ViewController.swift
igen_templates/base/ViewControllerTests.swift
igen_templates/base/ViewModel.swift
igen_templates/base/ViewModelTests.swift
igen_templates/commands/API.swift
igen_templates/commands/BindViewModel.swift
igen_templates/commands/FileHeader.swift
igen_templates/commands/Init.swift
igen_templates/commands/JSON.swift
igen_templates/commands/JSONClass.swift
igen_templates/commands/Mock.swift
igen_templates/commands/UnitTest.swift
igen_templates/detail/Assembler.swift
igen_templates/detail/Cell.swift
igen_templates/detail/CellsTests.swift
igen_templates/detail/Navigator.swift
igen_templates/detail/NavigatorMock.swift
igen_templates/detail/StaticViewController.swift
igen_templates/detail/StaticViewControllerTests.swift
igen_templates/detail/StaticViewModel.swift
igen_templates/detail/StaticViewModelTests.swift
igen_templates/detail/UseCase.swift
igen_templates/detail/UseCaseMock.swift
igen_templates/detail/ViewController.swift
igen_templates/detail/ViewControllerTests.swift
igen_templates/detail/ViewModel.swift
igen_templates/detail/ViewModelTests.swift
igen_templates/form/Assembler.swift
igen_templates/form/Cell.swift
igen_templates/form/CellsTests.swift
igen_templates/form/DynamicViewController.swift
igen_templates/form/DynamicViewControllerTests.swift
igen_templates/form/DynamicViewModel.swift
igen-3.0.0.dist-info/LICENSE
igen-3.0.0.dist-info/METADATA
igen-3.0.0.dist-info/WHEEL
igen-3.0.0.dist-info/entry_points.txt
igen-3.0.0.dist-info/top_level.txt
igen-3.0.0.dist-info/RECORD
