Metadata-Version: 2.1
Name: igen
Version: 3.0.0
Summary: A code generator for iOS
Home-page: https://github.com/tuan188/MGiGen
Author: Tuan Truong
Author-email: tuan188@gmail.com
License: MIT
Platform: UNKNOWN
Classifier: Programming Language :: Python :: 3
Classifier: License :: OSI Approved :: MIT License
Classifier: Operating System :: OS Independent
Requires-Python: >=3
Requires-Dist: Jinja2 (>=2.10)
Requires-Dist: arghandler (>=1.2)
